{"items":[
{"cost":100, "acqYear":2010, "category":"Machinery & Equipment"},
{"cost":100, "acqYear":2010, "category":"Machinery & Equipment"},
{"cost":100, "acqYear":2010, "category":"Machinery & Equipment"},
{"cost":100, "acqYear":2010, "category":"Machinery & Equipment"},
{"cost":100, "acqYear":2010, "category":"Machinery & Equipment"},
{"cost":100, "acqYear":2010, "category":"Machinery & Equipment"},
{"cost":100, "acqYear":2010, "category":"Machinery & Equipment"},
{"cost":100, "acqYear":2010, "category":"Machinery & Equipment"},
{"cost":100, "acqYear":2010, "category":"Machinery & Equipment"},
{"cost":100, "acqYear":2010, "category":"Machinery & Equipment"}
]}
